setup.py
aiomcache_multi/__init__.py
aiomcache_multi.egg-info/PKG-INFO
aiomcache_multi.egg-info/SOURCES.txt
aiomcache_multi.egg-info/dependency_links.txt
aiomcache_multi.egg-info/requires.txt
aiomcache_multi.egg-info/top_level.txt